chillbox/__init__.py
chillbox/_version.py
chillbox/defaults.py
chillbox/errors.py
chillbox/local_checks.py
chillbox/main.py
chillbox/scratch
chillbox/ssh.py
chillbox/state.py
chillbox/template.py
chillbox/utils.py
chillbox/validate.py
chillbox/data/__init__.py
chillbox/data/commands-info.toml
chillbox/data/scripts/__init__.py
chillbox/data/scripts/create-asymmetric-key
chillbox/data/scripts/decrypt-file
chillbox/data/scripts/encrypt-file
chillbox/data/scripts/init-s6-openrc-path-secret-watcher.sh
chillbox/data/templates/chillbox.nft
chillbox/data/templates/create_dirs-PATH_SECRETS.jinja
chillbox/data/templates/create_dirs-PATH_SENSITIVE.jinja
chillbox/data/templates/create_dirs.sh
chillbox/data/templates/s3-credentials.jinja
chillbox/data/templates/sshd_config
chillbox/data/templates/sshd_config--publickey_only
chillbox/data/templates/stream.nginx.conf.jinja
chillbox/data/templates/user-data.sh.jinja
chillbox/data/templates/user-data/dynamic/base--alpine.sh.jinja
chillbox/data/templates/user-data/static/base--alpine.sh.jinja
chillbox/data/templates/user-data/static/snippet-create_scripts.sh.jinja
chillbox/tasks/__init__.py
chillbox/tasks/hold--ephemeral-local-server.py
chillbox/tasks/local_archive.py
chillbox/tasks/local_env.py
chillbox/tasks/local_show.py
chillbox/tasks/local_ssh.py
chillbox/tasks/server.py
chillbox/templates/commands-info.jinja
chillbox/templates/local-process-path-errors.jinja
chillbox/templates/ssh_config.jinja
chillbox-0.0.1.dist-info/METADATA
chillbox-0.0.1.dist-info/WHEEL
chillbox-0.0.1.dist-info/entry_points.txt
chillbox-0.0.1.dist-info/licenses/LICENSE
chillbox-0.0.1.dist-info/RECORD
