Metadata-Version: 2.1
Name: chillbox
Version: 0.0.1
Summary: Deployment scripts for websites that use Chill and custom Python services. Work in Progress 
Project-URL: Homepage, https://git.sr.ht/~jkenlooper/chillbox
Project-URL: documentation, https://jkenlooper.srht.site/chillbox/
Project-URL: repository, https://git.sr.ht/~jkenlooper/chillbox
Project-URL: changelog, https://git.sr.ht/~jkenlooper/chillbox/tree/main/item/CHANGELOG.md
Author-email: Jake Hickenlooper <jake@massive.xyz>
License: ISCL
License-File: LICENSE
Classifier: Development Status :: 1 - Planning
Classifier: Environment :: Console
Classifier: Intended Audience :: Developers
Classifier: Intended Audience :: Information Technology
Classifier: License :: OSI Approved :: ISC License (ISCL)
Classifier: Natural Language :: English
Classifier: Operating System :: POSIX
Classifier: Programming Language :: Python :: 3.9
Classifier: Programming Language :: Python :: 3.10
Classifier: Programming Language :: Python :: 3.11
Classifier: Topic :: Internet :: WWW/HTTP :: Site Management
Classifier: Topic :: Software Development :: Build Tools
Requires-Python: <4,>=3.9
Requires-Dist: fabric>=3
Requires-Dist: httpx
Requires-Dist: invoke>=2
Requires-Dist: jinja2>=3.1
Requires-Dist: scp>=0.14
Requires-Dist: tomli>=1.1.0; python_version < '3.11'
Provides-Extra: dev
Provides-Extra: test
Requires-Dist: coverage; extra == 'test'
Requires-Dist: pytest; extra == 'test'
